jddf/__init__.py
jddf/schema.py
jddf/validator.py
jddf-0.1.0.dist-info/LICENSE
jddf-0.1.0.dist-info/METADATA
jddf-0.1.0.dist-info/WHEEL
jddf-0.1.0.dist-info/top_level.txt
jddf-0.1.0.dist-info/RECORD
