Metadata-Version: 2.1
Name: jddf
Version: 0.1.0
Summary: JSON Data Definition Format support for Python
Home-page: https://github.com/jddf/jddf-python
Author: Ulysse Carion
Author-email: ulysse@segment.com
License: UNKNOWN
Platform: UNKNOWN
Classifier: Programming Language :: Python :: 3
Classifier: License :: OSI Approved :: MIT License
Classifier: Operating System :: OS Independent
Requires-Python: >=3.6
Requires-Dist: strict-rfc3339 (==0.7)
